splunk_assistant_skills_lib/__init__.py
splunk_assistant_skills_lib/autocomplete_cache.py
splunk_assistant_skills_lib/config_manager.py
splunk_assistant_skills_lib/credential_manager.py
splunk_assistant_skills_lib/error_handler.py
splunk_assistant_skills_lib/formatters.py
splunk_assistant_skills_lib/job_poller.py
splunk_assistant_skills_lib/py.typed
splunk_assistant_skills_lib/search_context.py
splunk_assistant_skills_lib/spl_helper.py
splunk_assistant_skills_lib/splunk_client.py
splunk_assistant_skills_lib/time_utils.py
splunk_assistant_skills_lib/validators.py
splunk_assistant_skills_lib/cli/__init__.py
splunk_assistant_skills_lib/cli/cli_utils.py
splunk_assistant_skills_lib/cli/main.py
splunk_assistant_skills_lib/cli/commands/__init__.py
splunk_assistant_skills_lib/cli/commands/admin_cmds.py
splunk_assistant_skills_lib/cli/commands/alert_cmds.py
splunk_assistant_skills_lib/cli/commands/app_cmds.py
splunk_assistant_skills_lib/cli/commands/export_cmds.py
splunk_assistant_skills_lib/cli/commands/job_cmds.py
splunk_assistant_skills_lib/cli/commands/kvstore_cmds.py
splunk_assistant_skills_lib/cli/commands/lookup_cmds.py
splunk_assistant_skills_lib/cli/commands/metadata_cmds.py
splunk_assistant_skills_lib/cli/commands/metrics_cmds.py
splunk_assistant_skills_lib/cli/commands/savedsearch_cmds.py
splunk_assistant_skills_lib/cli/commands/search_cmds.py
splunk_assistant_skills_lib/cli/commands/security_cmds.py
splunk_assistant_skills_lib/cli/commands/tag_cmds.py
splunk_assistant_skills_lib/mock/__init__.py
splunk_assistant_skills_lib/mock/base.py
splunk_assistant_skills_lib/mock/client.py
splunk_assistant_skills_lib/mock/factories.py
splunk_assistant_skills_lib/mock/protocols.py
splunk_assistant_skills_lib/mock/mixins/__init__.py
splunk_assistant_skills_lib/mock/mixins/admin.py
splunk_assistant_skills_lib/mock/mixins/export.py
splunk_assistant_skills_lib/mock/mixins/job.py
splunk_assistant_skills_lib/mock/mixins/metadata.py
splunk_assistant_skills_lib/mock/mixins/search.py
splunk_assistant_skills_lib-1.0.1.dist-info/METADATA
splunk_assistant_skills_lib-1.0.1.dist-info/WHEEL
splunk_assistant_skills_lib-1.0.1.dist-info/entry_points.txt
splunk_assistant_skills_lib-1.0.1.dist-info/licenses/LICENSE
splunk_assistant_skills_lib-1.0.1.dist-info/RECORD
