Metadata-Version: 2.4
Name: splunk-assistant-skills-lib
Version: 1.0.1
Summary: Shared library for Splunk Assistant Skills - HTTP client, configuration management, error handling, and utilities for Splunk REST API automation
Project-URL: Homepage, https://github.com/grandcamel/splunk-assistant-skills-lib
Project-URL: Repository, https://github.com/grandcamel/splunk-assistant-skills-lib
Project-URL: Issues, https://github.com/grandcamel/splunk-assistant-skills-lib/issues
Project-URL: Changelog, https://github.com/grandcamel/splunk-assistant-skills-lib/blob/main/CHANGELOG.md
Author-email: Jason Krueger <grandcamel@gmail.com>
License-Expression: MIT
License-File: LICENSE
Keywords: api,assistant,automation,claude,rest,skills,splunk
Classifier: Development Status :: 4 - Beta
Classifier: Intended Audience :: Developers
Classifier: License :: OSI Approved :: MIT License
Classifier: Operating System :: OS Independent
Classifier: Programming Language :: Python :: 3
Classifier: Programming Language :: Python :: 3.9
Classifier: Programming Language :: Python :: 3.10
Classifier: Programming Language :: Python :: 3.11
Classifier: Programming Language :: Python :: 3.12
Classifier: Topic :: Software Development :: Libraries :: Python Modules
Classifier: Topic :: System :: Systems Administration
Requires-Python: >=3.9
Requires-Dist: assistant-skills-lib>=1.0.0
Requires-Dist: click>=8.0
Requires-Dist: requests>=2.28.0
Provides-Extra: dev
Requires-Dist: black>=23.0.0; extra == 'dev'
Requires-Dist: isort<6.0.0,>=5.12.0; extra == 'dev'
Requires-Dist: mypy>=1.0.0; extra == 'dev'
Requires-Dist: pytest-cov>=4.0.0; extra == 'dev'
Requires-Dist: pytest>=7.0.0; extra == 'dev'
Requires-Dist: types-requests>=2.28.0; extra == 'dev'
